{
  "$schema": "https://melvoridle.com/assets/schema/gameData.json",
  "namespace": "adventuring",
  "data": {
    "skillLevelCapIncreases": [
      {
        "id": "Pre99Dungeons",
        "levelType": "Standard",
        "requirementSets": [
          {
            "id": 0,
            "requirements": [
              {
                "type": "DungeonCompletion",
                "dungeonID": "melvorD:Chicken_Coop",
                "count": 1
              }
            ]
          },
          {
            "id": 1,
            "requirements": [
              {
                "type": "DungeonCompletion",
                "dungeonID": "melvorD:Undead_Graveyard",
                "count": 1
              }
            ]
          },
          {
            "id": 2,
            "requirements": [
              {
                "type": "DungeonCompletion",
                "dungeonID": "melvorD:Spider_Forest",
                "count": 1
              }
            ]
          },
          {
            "id": 3,
            "requirements": [
              {
                "type": "DungeonCompletion",
                "dungeonID": "melvorD:Frozen_Cove",
                "count": 1
              }
            ]
          },
          {
            "id": 4,
            "requirements": [
              {
                "type": "DungeonCompletion",
                "dungeonID": "melvorD:Deep_Sea_Ship",
                "count": 1
              }
            ]
          },
          {
            "id": 5,
            "requirements": [
              {
                "type": "DungeonCompletion",
                "dungeonID": "melvorD:Volcanic_Cave",
                "count": 1
              }
            ]
          },
          {
            "id": 6,
            "requirements": [
              {
                "type": "DungeonCompletion",
                "dungeonID": "melvorD:Bandit_Base",
                "count": 1
              }
            ]
          },
          {
            "id": 7,
            "requirements": [
              {
                "type": "DungeonCompletion",
                "dungeonID": "melvorD:Hall_of_Wizards",
                "count": 1
              }
            ]
          },
          {
            "id": 8,
            "requirements": [
              {
                "type": "DungeonCompletion",
                "dungeonID": "melvorF:Air_God_Dungeon",
                "count": 1
              }
            ]
          },
          {
            "id": 9,
            "requirements": [
              {
                "type": "DungeonCompletion",
                "dungeonID": "melvorF:Water_God_Dungeon",
                "count": 1
              }
            ]
          },
          {
            "id": 10,
            "requirements": [
              {
                "type": "DungeonCompletion",
                "dungeonID": "melvorF:Earth_God_Dungeon",
                "count": 1
              }
            ]
          },
          {
            "id": 11,
            "requirements": [
              {
                "type": "DungeonCompletion",
                "dungeonID": "melvorF:Fire_God_Dungeon",
                "count": 1
              }
            ]
          },
          {
            "id": 12,
            "requirements": [
              {
                "type": "DungeonCompletion",
                "dungeonID": "melvorF:Dragons_Den",
                "count": 1
              }
            ]
          },
          {
            "id": 13,
            "requirements": [
              {
                "type": "DungeonCompletion",
                "dungeonID": "melvorF:Miolite_Caves",
                "count": 1
              }
            ]
          },
          {
            "id": 14,
            "requirements": [
              {
                "type": "DungeonCompletion",
                "dungeonID": "melvorF:Infernal_Stronghold",
                "count": 1
              }
            ]
          },
          {
            "id": 15,
            "requirements": [
              {
                "type": "DungeonCompletion",
                "dungeonID": "melvorF:Into_the_Mist",
                "count": 1
              }
            ]
          },
          {
            "id": 16,
            "requirements": [
              {
                "type": "DungeonCompletion",
                "dungeonID": "melvorF:Impending_Darkness",
                "count": 1
              }
            ]
          },
          {
            "id": 17,
            "requirements": [
              {
                "type": "DungeonCompletion",
                "dungeonID": "melvorAoD:Golem_Territory",
                "count": 1
              }
            ]
          },
          {
            "id": 18,
            "requirements": [
              {
                "type": "DungeonCompletion",
                "dungeonID": "melvorAoD:Unholy_Forest",
                "count": 1
              }
            ]
          },
          {
            "id": 19,
            "requirements": [
              {
                "type": "DungeonCompletion",
                "dungeonID": "melvorAoD:Trickery_Temple",
                "count": 1
              }
            ]
          },
          {
            "id": 20,
            "requirements": [
              {
                "type": "DungeonCompletion",
                "dungeonID": "melvorAoD:Cult_Grounds",
                "count": 1
              }
            ]
          },
          {
            "id": 21,
            "requirements": [
              {
                "type": "DungeonCompletion",
                "dungeonID": "melvorAoD:Underwater_City",
                "count": 1
              }
            ]
          }
        ],
        "fixedIncreases": [
          {
            "skillID": "adventuring:Adventuring",
            "increase": 5,
            "maximum": 99
          }
        ]
      },
      {
        "id": "ImpendingDarknessSet100",
        "levelType": "Standard",
        "requirementSets": [
          {
            "id": 0,
            "requirements": [
              {
                "type": "DungeonCompletion",
                "dungeonID": "melvorF:Impending_Darkness",
                "count": 1
              }
            ]
          }
        ],
        "setIncreases": [
          {
            "skillID": "adventuring:Adventuring",
            "value": 100
          }
        ]
      }
    ]
  },
  "dependentData": [
    {
      "namespace": "melvorTotH",
      "data": {
        "skillLevelCapIncreases": [
          {
            "id": "Post99Dungeons",
            "levelType": "Standard",
            "requirementSets": [
              {
                "id": 0,
                "requirements": [
                  {
                    "type": "DungeonCompletion",
                    "dungeonID": "melvorTotH:Ancient_Sanctuary",
                    "count": 1
                  }
                ]
              },
              {
                "id": 1,
                "requirements": [
                  {
                    "type": "DungeonCompletion",
                    "dungeonID": "melvorTotH:Underground_Lava_Lake",
                    "count": 1
                  }
                ]
              },
              {
                "id": 2,
                "requirements": [
                  {
                    "type": "DungeonCompletion",
                    "dungeonID": "melvorTotH:Lightning_Region",
                    "count": 1
                  }
                ]
              },
              {
                "id": 3,
                "requirements": [
                  {
                    "type": "DungeonCompletion",
                    "dungeonID": "melvorTotH:Lair_of_the_Spider_Queen",
                    "count": 1
                  }
                ]
              },
              {
                "id": 4,
                "requirements": [
                  {
                    "type": "DungeonCompletion",
                    "dungeonID": "melvorTotH:Cursed_Forest",
                    "count": 1
                  }
                ]
              },
              {
                "id": 5,
                "requirements": [
                  {
                    "type": "DungeonCompletion",
                    "dungeonID": "melvorTotH:Necromancers_Palace",
                    "count": 1
                  }
                ]
              },
              {
                "id": 6,
                "requirements": [
                  {
                    "type": "DungeonCompletion",
                    "dungeonID": "melvorTotH:Throne_of_the_Herald",
                    "count": 1
                  }
                ]
              }
            ],
            "fixedIncreases": [
              {
                "skillID": "adventuring:Adventuring",
                "increase": 3,
                "maximum": 120
              }
            ]
          },
          {
            "id": "ThroneOfTheHeraldSet120",
            "levelType": "Standard",
            "requirementSets": [
              {
                "id": 0,
                "requirements": [
                  {
                    "type": "DungeonCompletion",
                    "dungeonID": "melvorTotH:Throne_of_the_Herald",
                    "count": 1
                  }
                ]
              }
            ],
            "setIncreases": [
              {
                "skillID": "adventuring:Adventuring",
                "value": 120
              }
            ]
          }
        ]
      }
    }
  ]
}
